anacal/__init__.py
anacal/__version__.py
anacal/_anacal.cpython-312-x86_64-linux-gnu.so
anacal/_anacalLib.cc
anacal/fpfs.py
anacal/psf.py
anacal/simulation.py
anacal/utils.py
anacal/data/README.md
anacal/data/noise_correlation.fits
anacal/data/src_cosmos.fits
anacal.libs/libfftw3-6b983104.so.3.5.5
anacal.libs/libgomp-e985bcbb.so.1.0.0
anacal-0.7.1.dist-info/METADATA
anacal-0.7.1.dist-info/WHEEL
anacal-0.7.1.dist-info/top_level.txt
anacal-0.7.1.dist-info/RECORD
anacal-0.7.1.dist-info/licenses/LICENSE
