Metadata-Version: 2.4
Name: anacal
Version: 0.7.1
Home-page: https://github.com/mr-superonion/AnaCal/
Author: Xiangchong Li
Author-email: mr.superonion@hotmail.com
Requires-Python: >=3.10
License-File: LICENSE
Requires-Dist: pybind11>=2.2
Requires-Dist: numpy
Requires-Dist: galsim
Requires-Dist: fitsio
Requires-Dist: pydantic
Dynamic: author
Dynamic: author-email
Dynamic: description
Dynamic: description-content-type
Dynamic: home-page
Dynamic: license-file
Dynamic: requires-dist
Dynamic: requires-python
